action_sdk_for_cache/__init__.py
action_sdk_for_cache/action_cache_sdk.py
action_sdk_for_cache/baseClass/__init__.py
action_sdk_for_cache/baseClass/action_sdk_base.py
action_sdk_for_cache_mock-3.3.dist-info/METADATA
action_sdk_for_cache_mock-3.3.dist-info/WHEEL
action_sdk_for_cache_mock-3.3.dist-info/top_level.txt
action_sdk_for_cache_mock-3.3.dist-info/RECORD
