Metadata-Version: 2.1
Name: action-sdk-for-cache-mock
Version: 3.3
Summary: sdk used for honeyguide app
Home-page: UNKNOWN
Author: flagify
License: MIT
Platform: UNKNOWN
Classifier: Development Status :: 3 - Alpha
Classifier: Intended Audience :: Developers
Classifier: License :: OSI Approved :: MIT License
Classifier: Programming Language :: Python :: 3.6
Requires-Python: >=3.6
Requires-Dist: requests
